face_detection/__init__.py
face_detection/base.py
face_detection/box_utils.py
face_detection/build.py
face_detection/registry.py
face_detection/torch_utils.py
face_detection/dsfd/__init__.py
face_detection/dsfd/config.py
face_detection/dsfd/detect.py
face_detection/dsfd/face_ssd.py
face_detection/dsfd/utils.py
face_detection/retinaface/__init__.py
face_detection/retinaface/config.py
face_detection/retinaface/detect.py
face_detection/retinaface/prior_box.py
face_detection/retinaface/utils.py
face_detection/retinaface/models/__init__.py
face_detection/retinaface/models/net.py
face_detection/retinaface/models/retinaface.py
face_detection-0.1.4.dist-info/LICENSE
face_detection-0.1.4.dist-info/METADATA
face_detection-0.1.4.dist-info/WHEEL
face_detection-0.1.4.dist-info/top_level.txt
face_detection-0.1.4.dist-info/RECORD
