Metadata-Version: 2.1
Name: face-detection
Version: 0.1.4
Summary: A simple and lightweight package for state of the art face detection with GPU support.
Home-page: https://github.com/hukkelas/DSFD-Pytorch-Inference
Author: Håkon Hukkelås
License: apache-2.0
Platform: UNKNOWN
Classifier: License :: OSI Approved :: Apache Software License
Classifier: Operating System :: OS Independent
Requires-Python: >=3.6
Requires-Dist: torch (>=1.1)
Requires-Dist: torchvision (>=0.3.0)
Requires-Dist: numpy
